audio2numpy/__init__.py
audio2numpy/exceptions.py
audio2numpy/loader.py
audio2numpy/mp3dec.py
audio2numpy/version.py
audio2numpy/wavdec.py
audio2numpy-0.1.2.dist-info/LICENSE
audio2numpy-0.1.2.dist-info/METADATA
audio2numpy-0.1.2.dist-info/WHEEL
audio2numpy-0.1.2.dist-info/top_level.txt
audio2numpy-0.1.2.dist-info/RECORD
