Metadata-Version: 2.1
Name: audio2numpy
Version: 0.1.2
Summary: Load audio file to numpy array
Home-page: https://github.com/wiccy46/audio2numpy
Author: Jiajun Yang
Author-email: thejyang@gmail.com
License: MIT
Keywords: audio, audio reader
Platform: UNKNOWN
Classifier: Topic :: Multimedia :: Sound/Audio
Classifier: Topic :: Multimedia :: Sound/Audio :: Conversion
Classifier: Programming Language :: Python :: 2.7
Classifier: Programming Language :: Python :: 3.5
Classifier: Programming Language :: Python :: 3.6
Classifier: Programming Language :: Python :: 3.7
